pychords/__init__.py
pychords/chord_types.py
pychords/chords.py
pychords/modes.py
pychords/notes.py
pychords/scales.py
pychords/transpose.py
pychords-0.0.5.dist-info/LICENSE
pychords-0.0.5.dist-info/METADATA
pychords-0.0.5.dist-info/WHEEL
pychords-0.0.5.dist-info/top_level.txt
pychords-0.0.5.dist-info/RECORD
